# Libraries
JIT exclusive built in libraries.
> **NOTE**: These will not work in the interpreter, only the JIT. But the interpreter's built in libraries will work in the JIT.
## `bc`
This library is bytecode listing.</br>
**Type:** `CLI`</br>
> This is based from LuaJIT's `bc` library.
### Example:
```bash
cobaltjit -jbc -e 'var x=0; for (i=1,1e6) { x=x+i } print(x)'
```
#### Output:
```bash
-- BYTECODE -- (command line):0-1
KGC    0    "print"
0001    KSHORT   0   0
0002    KSHORT   1   1
0003    KNUM     2   0      ; 1000000
0004    KSHORT   3   1
0005    FORI     1 => 0008
0006 => ADDVV    0   0   4
0007    FORL     1 => 0006
0008 => GGET     1   0      ; "print"
0009    MOV      3   0
0010    CALL     1   1   2
0011    RET0     0   1

500000500000
```
## `bcsave`
This library is bytecode saving.</br>
**Type:** `CLI`</br>
> This is based from LuaJIT's `bcsave` library.
This library is also is used for bytecode dumping.
### Options:
```bash
  -l        Only list bytecode.
  -L        Only list bytecode with lineinfo.
  -s        Strip debug info (default).
  -g        Keep debug info.
  -n name   Set module name (default: auto-detect from input name).
  -t type   Set output file type (default: auto-detect from output name).
  -a arch   Override architecture for object files (default: native).
  -o os     Override OS for object files (default: native).
  -e chunk  Use chunk string as input.
  --        Stop handling options.
  -         Use stdin as input and/or stdout as output.
```
### Example:
```bash
cobaltjit -bl -e 'var x=0; for (i=1,1e6) { x=x+i } pri
nt(x)'
```
#### Output:
```bash
-- BYTECODE -- 0x025c9568:0-1
KGC    0    "print"
0001    KSHORT   0   0
0002    KSHORT   1   1
0003    KNUM     2   0      ; 1000000
0004    KSHORT   3   1
0005    FORI     1 => 0008
0006 => ADDVV    0   0   4
0007    FORL     1 => 0006
0008 => GGET     1   0      ; "print"
0009    MOV      3   0
0010    CALL     1   1   2
0011    RET0     0   1
```
## `dis_x64` & `dis_x86`
This library is x64 disassembler. Used internally, not recommended for use.</br>
**Type:** `CLI`</br>
> This is based from LuaJIT's `dis_x64` library.
## `dump`
Another bytecode dumper, this is the best one to use for outputting bytecode.</br>
**Type:** `CLI`</br>
> This is based from LuaJIT's `dump` library.
### Example:
```bash
cobaltjit -jdump -e 'var x=0; for (i=1,1e6) { x=x+i } print(x)'
```
#### Output:
```bash
-- BYTECODE -- 0x025c9568:0-1
KGC    0    "print"
0001    KSHORT   0   0
0002    KSHORT   1   1
0003    KNUM     2   0      ; 1000000
0004    KSHORT   3   1
0005    FORI     1 => 0008
0006 => ADDVV    0   0   4
0007    FORL     1 => 0006
0008 => GGET     1   0      ; "print"
0009    MOV      3   0
0010    CALL     1   1   2
0011    RET0     0   1

Aaravs-Awesome-MacBook-Pro:cobalt-docs aaravs$ cobaltjit -jdump -e 'var x=0; for (i=1,1e6) { x=x+i } print(x)'
---- TRACE 1 start (command line):1
0006  ADDVV    0   0   4       ((command line):1)
0007  FORL     1 => 0006       ((command line):1)
---- TRACE 1 IR
0001    int SLOAD  #3    CI
0002 >  num SLOAD  #2    T
0003    num CONV   0001  num.int
0004  + num ADD    0003  0002
0005  + int ADD    0001  +1  
0006 >  int LE     0005  +1000000
0007 ------ LOOP ------------
0008    num CONV   0005  num.int
0009  + num ADD    0008  0004
0010  + int ADD    0005  +1  
0011 >  int LE     0010  +1000000
0012    int PHI    0005  0010
0013    num PHI    0004  0009
---- TRACE 1 mcode 82
VM handler failed: /usr/local/share/lua/cobalt/jit/dump.cobalt:111: attempt to compare null with number
```
### Perks:
- Outputs cleaner bytecode.
- Outputs error messages.
- Traces.
## `loom`
Export HTML file for analysing bytecode. [read more](/debugging/3.loom.md)</br>
**Type:** `CLI`</br>
> This is based from Cloudflare's `loom` library.
